weather_forecast_information/__init__.py
weather_forecast_information/city.txt
weather_forecast_information/cli.py
weather_forecast_information/main.py
weather_forecast_information/weather_output.txt
weather_forecast_information-0.1.1.dist-info/METADATA
weather_forecast_information-0.1.1.dist-info/WHEEL
weather_forecast_information-0.1.1.dist-info/entry_points.txt
weather_forecast_information-0.1.1.dist-info/RECORD
